invenio_testing/__init__.py
invenio_testing/version.py
invenio_testing/translations/invenio.pot
invenio_testing/translations/de/LC_MESSAGES/messages.mo
invenio_testing/translations/de/LC_MESSAGES/messages.po
invenio_testing/translations/es/LC_MESSAGES/messages.mo
invenio_testing/translations/es/LC_MESSAGES/messages.po
invenio_testing/translations/fr/LC_MESSAGES/messages.mo
invenio_testing/translations/fr/LC_MESSAGES/messages.po
invenio_testing/translations/it/LC_MESSAGES/messages.mo
invenio_testing/translations/it/LC_MESSAGES/messages.po
invenio_testing-0.1.1.dist-info/top_level.txt
invenio_testing-0.1.1.dist-info/METADATA
invenio_testing-0.1.1.dist-info/DESCRIPTION.rst
invenio_testing-0.1.1.dist-info/metadata.json
invenio_testing-0.1.1.dist-info/WHEEL
invenio_testing-0.1.1.dist-info/RECORD
