Metadata-Version: 2.0
Name: invenio-testing
Version: 0.1.1
Summary: The Invenio-Testing provides unit testing utilities for Invenio.
Home-page: https://github.com/inveniosoftware/invenio-testing
Author: CERN
Author-email: info@invenio-software.org
License: GPLv2
Keywords: invenio testing
Platform: any
Classifier: Environment :: Web Environment
Classifier: Intended Audience :: Developers
Classifier: License :: OSI Approved :: GNU General Public License v2 (GPLv2)
Classifier: Operating System :: OS Independent
Classifier: Programming Language :: Python
Classifier: Topic :: Internet :: WWW/HTTP :: Dynamic Content
Classifier: Topic :: Software Development :: Libraries :: Python Modules
Classifier: Programming Language :: Python :: 2
Classifier: Programming Language :: Python :: 2.7
Classifier: Development Status :: 1 - Planning
Requires-Dist: Flask-Testing (>=0.4.1)
Requires-Dist: Flask (>=0.10.1)
Requires-Dist: coverage (>=4.0.0)
Requires-Dist: invenio-base (>=0.3.0)
Requires-Dist: invenio-ext (>=0.2.0)
Requires-Dist: pytest-cov (>=2.1.0)
Requires-Dist: pytest-pep8 (>=1.0.6)
Requires-Dist: pytest (>=2.8.0)
Requires-Dist: reportlab (>=2.7,<3.2)
Requires-Dist: six (>=1.7.2)
Provides-Extra: docs
Requires-Dist: Sphinx (>=1.3); extra == 'docs'
Requires-Dist: sphinx-rtd-theme (>=0.1.7); extra == 'docs'
